{"nodes": [{"id": "c_users_frederico_workspace_quiz_codacy_cli_sh", "label": "cli.sh", "file_type": "code", "source_file": ".codacy/cli.sh", "source_location": "L1", "metadata": {"language": "bash", "kind": "file"}}, {"id": "c_users_frederico_workspace_quiz_codacy_cli_sh__entry", "label": "cli.sh script", "file_type": "code", "source_file": ".codacy/cli.sh", "source_location": "L1", "metadata": {"language": "bash", "kind": "bash_entrypoint"}}, {"id": "codacy_cli_get_version_from_yaml", "label": "get_version_from_yaml()", "file_type": "code", "source_file": ".codacy/cli.sh", "source_location": "L38", "metadata": {"language": "bash", "kind": "bash_function"}}, {"id": "codacy_cli_get_latest_version", "label": "get_latest_version()", "file_type": "code", "source_file": ".codacy/cli.sh", "source_location": "L49", "metadata": {"language": "bash", "kind": "bash_function"}}, {"id": "codacy_cli_handle_rate_limit", "label": "handle_rate_limit()", "file_type": "code", "source_file": ".codacy/cli.sh", "source_location": "L62", "metadata": {"language": "bash", "kind": "bash_function"}}, {"id": "codacy_cli_download_file", "label": "download_file()", "file_type": "code", "source_file": ".codacy/cli.sh", "source_location": "L69", "metadata": {"language": "bash", "kind": "bash_function"}}, {"id": "codacy_cli_download", "label": "download()", "file_type": "code", "source_file": ".codacy/cli.sh", "source_location": "L82", "metadata": {"language": "bash", "kind": "bash_function"}}, {"id": "codacy_cli_download_cli", "label": "download_cli()", "file_type": "code", "source_file": ".codacy/cli.sh", "source_location": "L89", "metadata": {"language": "bash", "kind": "bash_function"}}], "edges": [{"source": "c_users_frederico_workspace_quiz_codacy_cli_sh", "target": "c_users_frederico_workspace_quiz_codacy_cli_sh__entry", "relation": "contains", "confidence": "EXTRACTED", "source_file": ".codacy/cli.sh", "source_location": "L1", "weight": 1.0}, {"source": "c_users_frederico_workspace_quiz_codacy_cli_sh", "target": "codacy_cli_get_version_from_yaml", "relation": "defines", "confidence": "EXTRACTED", "source_file": ".codacy/cli.sh", "source_location": "L38", "weight": 1.0}, {"source": "c_users_frederico_workspace_quiz_codacy_cli_sh", "target": "codacy_cli_get_latest_version", "relation": "defines", "confidence": "EXTRACTED", "source_file": ".codacy/cli.sh", "source_location": "L49", "weight": 1.0}, {"source": "c_users_frederico_workspace_quiz_codacy_cli_sh", "target": "codacy_cli_handle_rate_limit", "relation": "defines", "confidence": "EXTRACTED", "source_file": ".codacy/cli.sh", "source_location": "L62", "weight": 1.0}, {"source": "c_users_frederico_workspace_quiz_codacy_cli_sh", "target": "codacy_cli_download_file", "relation": "defines", "confidence": "EXTRACTED", "source_file": ".codacy/cli.sh", "source_location": "L69", "weight": 1.0}, {"source": "c_users_frederico_workspace_quiz_codacy_cli_sh", "target": "codacy_cli_download", "relation": "defines", "confidence": "EXTRACTED", "source_file": ".codacy/cli.sh", "source_location": "L82", "weight": 1.0}, {"source": "c_users_frederico_workspace_quiz_codacy_cli_sh", "target": "codacy_cli_download_cli", "relation": "defines", "confidence": "EXTRACTED", "source_file": ".codacy/cli.sh", "source_location": "L89", "weight": 1.0}, {"source": "c_users_frederico_workspace_quiz_codacy_cli_sh__entry", "target": "codacy_cli_download_cli", "relation": "calls", "confidence": "EXTRACTED", "source_file": ".codacy/cli.sh", "source_location": "L137", "weight": 1.0, "context": "call"}, {"source": "codacy_cli_get_latest_version", "target": "codacy_cli_handle_rate_limit", "relation": "calls", "confidence": "EXTRACTED", "source_file": ".codacy/cli.sh", "source_location": "L57", "weight": 1.0, "context": "call"}, {"source": "codacy_cli_download", "target": "codacy_cli_download_file", "relation": "calls", "confidence": "EXTRACTED", "source_file": ".codacy/cli.sh", "source_location": "L86", "weight": 1.0, "context": "call"}, {"source": "codacy_cli_download_cli", "target": "codacy_cli_download", "relation": "calls", "confidence": "EXTRACTED", "source_file": ".codacy/cli.sh", "source_location": "L103", "weight": 1.0, "context": "call"}]}